ir_datasets_longeval/__init__.py
ir_datasets_longeval/__main__.py
ir_datasets_longeval/bibliography.bib
ir_datasets_longeval/formats.py
ir_datasets_longeval/util.py
ir_datasets_longeval/datasets/longeval_2023.py
ir_datasets_longeval/datasets/longeval_sci.py
ir_datasets_longeval/datasets/longeval_web.py
ir_datasets_longeval/docs/longeval_2023.yaml
ir_datasets_longeval/docs/longeval_sci.yaml
ir_datasets_longeval/docs/longeval_web.yaml
ir_datasets_longeval/etc/downloads.json
ir_datasets_longeval/etc/metadata.json
ir_datasets_longeval-0.0.11.dist-info/LICENSE
ir_datasets_longeval-0.0.11.dist-info/METADATA
ir_datasets_longeval-0.0.11.dist-info/WHEEL
ir_datasets_longeval-0.0.11.dist-info/entry_points.txt
ir_datasets_longeval-0.0.11.dist-info/top_level.txt
ir_datasets_longeval-0.0.11.dist-info/RECORD
