Metadata-Version: 2.2
Name: ir-datasets-longeval
Version: 0.0.11
Summary: Extension for accessing the LongEval test collections via ir_datasets.
Author-email: Jüri Keller <jueri.keller@th-koeln.de>, Jan Heinrich Merker <heinrich.merker@uni-jena.de>, Maik Fröbe <maik.froebe@uni-jena.de>
Project-URL: Bug Tracker, https://github.com/jueri/ir-datasets-longeval/issues
Project-URL: Homepage, https://github.com/jueri/ir-datasets-longeval
Classifier: Programming Language :: Python :: 3
Classifier: Programming Language :: Python :: 3 :: Only
Classifier: Programming Language :: Python :: 3.10
Classifier: Programming Language :: Python :: 3.11
Classifier: License :: OSI Approved :: MIT License
Classifier: Operating System :: OS Independent
Classifier: Intended Audience :: Science/Research
Classifier: Topic :: Scientific/Engineering
Requires-Python: >=3.10
License-File: LICENSE
Requires-Dist: fastwarc<0.16,>=0.14
Requires-Dist: importlib-metadata<9,>=7
Requires-Dist: ir-datasets~=0.5.6
Requires-Dist: pyyaml~=6.0
Requires-Dist: typing-extensions~=4.11
Provides-Extra: tests
Requires-Dist: bandit[toml]~=1.7; extra == "tests"
Requires-Dist: mypy~=1.5; extra == "tests"
Requires-Dist: pytest~=8.0; extra == "tests"
Requires-Dist: pytest-cov~=5.0; extra == "tests"
Requires-Dist: pytest-subtests<0.15.0,>=0.12.1; extra == "tests"
Requires-Dist: ruff<0.10,>=0.5.0; extra == "tests"
Requires-Dist: types-pyyaml~=6.0; extra == "tests"
Requires-Dist: parameterized<0.9.0; extra == "tests"
